{
	"type": "minecraft:chest",
	"pools": [
		{
			"name": "main",
			"rolls": {
				"type": "minecraft:uniform",
				"min": 1.0,
				"max": 2.0
			},
			"bonus_rolls": 0.0,
			"entries": [
				{
					"type": "minecraft:item",
					"conditions": [
						{
							"condition": "minecraft:random_chance",
							"chance": 0.25
						}
					],
					"name": "cobblemon:red_apricorn_seed"
				},
				{
					"type": "minecraft:item",
					"conditions": [
						{
							"condition": "minecraft:random_chance",
							"chance": 0.25
						}
					],
					"name": "cobblemon:blue_apricorn_seed"
				},
				{
					"type": "minecraft:item",
					"conditions": [
						{
							"condition": "minecraft:random_chance",
							"chance": 0.25
						}
					],
					"name": "cobblemon:green_apricorn_seed"
				},
				{
					"type": "minecraft:item",
					"conditions": [
						{
							"condition": "minecraft:random_chance",
							"chance": 0.25
						}
					],
					"name": "cobblemon:pink_apricorn_seed"
				},
				{
					"type": "minecraft:item",
					"conditions": [
						{
							"condition": "minecraft:random_chance",
							"chance": 0.25
						}
					],
					"name": "cobblemon:yellow_apricorn_seed"
				},
				{
					"type": "minecraft:item",
					"conditions": [
						{
							"condition": "minecraft:random_chance",
							"chance": 0.25
						}
					],
					"name": "cobblemon:white_apricorn_seed"
				},
				{
					"type": "minecraft:item",
					"conditions": [
						{
							"condition": "minecraft:random_chance",
							"chance": 0.25
						}
					],
					"name": "cobblemon:black_apricorn_seed"
				}
			],
			"conditions": [
				{
					"condition": "minecraft:random_chance",
					"chance": 0.185
				}
			]
		},
		{
			"name": "pool1",
			"rolls": 1.0,
			"bonus_rolls": 0.0,
			"entries": [
				{
					"type": "minecraft:item",
					"weight": 3,
					"functions": [
						{
							"function": "minecraft:set_count",
							"count": 5.0,
							"add": false
						}
					],
					"name": "cobblemon:poke_ball"
				},
				{
					"type": "minecraft:item",
					"weight": 2,
					"functions": [
						{
							"function": "minecraft:set_count",
							"count": 5.0,
							"add": false
						}
					],
					"name": "cobblemon:citrine_ball"
				},
				{
					"type": "minecraft:item",
					"weight": 2,
					"functions": [
						{
							"function": "minecraft:set_count",
							"count": 5.0,
							"add": false
						}
					],
					"name": "cobblemon:verdant_ball"
				},
				{
					"type": "minecraft:item",
					"weight": 2,
					"functions": [
						{
							"function": "minecraft:set_count",
							"count": 5.0,
							"add": false
						}
					],
					"name": "cobblemon:azure_ball"
				},
				{
					"type": "minecraft:item",
					"weight": 2,
					"functions": [
						{
							"function": "minecraft:set_count",
							"count": 5.0,
							"add": false
						}
					],
					"name": "cobblemon:slate_ball"
				},
				{
					"type": "minecraft:item",
					"weight": 2,
					"functions": [
						{
							"function": "minecraft:set_count",
							"count": 5.0,
							"add": false
						}
					],
					"name": "cobblemon:roseate_ball"
				},
				{
					"type": "minecraft:item",
					"functions": [
						{
							"function": "minecraft:set_count",
							"count": 5.0,
							"add": false
						}
					],
					"name": "cobblemon:premier_ball"
				}
			]
		}
	]
}