{
	"type": "minecraft:chest",
	"pools": [
		{
			"name": "main",
			"rolls": {
				"type": "minecraft:uniform",
				"min": 4.0,
				"max": 6.0
			},
			"bonus_rolls": 0.0,
			"entries": [
				{
					"type": "minecraft:item",
					"weight": 5,
					"functions": [
						{
							"function": "minecraft:set_count",
							"count": {
								"type": "minecraft:uniform",
								"min": 4.0,
								"max": 25.0
							},
							"add": false
						}
					],
					"name": "minecraft:quartz"
				},
				{
					"type": "minecraft:item",
					"weight": 4,
					"functions": [
						{
							"function": "minecraft:set_count",
							"count": {
								"type": "minecraft:uniform",
								"min": 1.0,
								"max": 6.0
							},
							"add": false
						}
					],
					"name": "minecraft:echo_shard"
				},
				{
					"type": "minecraft:item",
					"weight": 5,
					"functions": [
						{
							"function": "minecraft:set_count",
							"count": {
								"type": "minecraft:uniform",
								"min": 4.0,
								"max": 6.0
							},
							"add": false
						}
					],
					"name": "minecraft:amethyst_shard"
				},
				{
					"type": "minecraft:item",
					"weight": 5,
					"functions": [
						{
							"function": "minecraft:set_count",
							"count": {
								"type": "minecraft:uniform",
								"min": 4.0,
								"max": 6.0
							},
							"add": false
						}
					],
					"name": "minecraft:glistering_melon_slice"
				},
				{
					"type": "minecraft:item",
					"weight": 5,
					"functions": [
						{
							"function": "minecraft:set_count",
							"count": {
								"type": "minecraft:uniform",
								"min": 1.0,
								"max": 6.0
							},
							"add": false
						}
					],
					"name": "minecraft:glowstone_dust"
				},
				{
					"type": "minecraft:item",
					"weight": 6,
					"functions": [
						{
							"function": "minecraft:set_count",
							"count": {
								"type": "minecraft:uniform",
								"min": 1.0,
								"max": 6.0
							},
							"add": false
						}
					],
					"name": "minecraft:string"
				},
				{
					"type": "minecraft:item",
					"weight": 5,
					"functions": [
						{
							"function": "minecraft:set_count",
							"count": {
								"type": "minecraft:uniform",
								"min": 1.0,
								"max": 6.0
							},
							"add": false
						}
					],
					"name": "minecraft:amethyst_block"
				},
				{
					"type": "minecraft:item",
					"weight": 2,
					"functions": [
						{
							"function": "minecraft:set_count",
							"count": {
								"type": "minecraft:uniform",
								"min": 1.0,
								"max": 6.0
							},
							"add": false
						}
					],
					"name": "minecraft:large_amethyst_bud"
				}
			]
		},
		{
			"name": "pool1",
			"rolls": 1.0,
			"bonus_rolls": 0.0,
			"entries": [
				{
					"type": "minecraft:item",
					"conditions": [
						{
							"condition": "minecraft:random_chance",
							"chance": 0.5
						}
					],
					"name": "minecraft:heart_of_the_sea"
				},
				{
					"type": "minecraft:item",
					"functions": [
						{
							"function": "minecraft:set_count",
							"count": {
								"type": "minecraft:uniform",
								"min": 2.0,
								"max": 8.0
							},
							"add": false
						}
					],
					"name": "minecraft:experience_bottle"
				},
				{
					"type": "minecraft:item",
					"conditions": [
						{
							"condition": "minecraft:random_chance",
							"chance": 0.4
						}
					],
					"functions": [
						{
							"function": "minecraft:set_nbt",
							"tag": "{Enchantments:[{id:\"knockback\",lvl:2},{id:\"mending\",lvl:1}],display:{Lore:['[\"\",{\"text\":\"YummY!\",\"italic\":false,\"color\":\"white\"}]'],Name:'[\"\",{\"text\":\"Polluted Water\",\"italic\":false,\"color\":\"#ccffcc\"}]'}}"
						}
					],
					"name": "minecraft:water_bucket"
				},
				{
					"type": "minecraft:item",
					"conditions": [
						{
							"condition": "minecraft:random_chance",
							"chance": 0.4
						}
					],
					"functions": [
						{
							"function": "minecraft:set_nbt",
							"tag": "{Enchantments:[{id:\"fortune\",lvl:3},{id:\"knockback\",lvl:2},{id:\"mending\",lvl:1},{id:\"silk_touch\",lvl:1}],display:{Lore:['[\"\",{\"text\":\"Old but still strong\",\"italic\":false,\"color\":\"white\"}]'],Name:'[\"\",{\"text\":\"Old Mans Stick\",\"italic\":false,\"color\":\"#006633\"}]'}}"
						}
					],
					"name": "minecraft:stick"
				},
				{
					"type": "minecraft:item",
					"functions": [
						{
							"function": "minecraft:set_count",
							"count": {
								"type": "minecraft:uniform",
								"min": 6.0,
								"max": 15.0
							},
							"add": false
						},
						{
							"function": "minecraft:set_nbt",
							"tag": "{CustomPotionColor:16777215,CustomPotionEffects:[{Duration:800,Id:2},{Amplifier:1,Duration:800,Id:18}],display:{Lore:['[\"\",{\"text\":\"Has good precision\",\"italic\":false,\"color\":\"white\"}]'],Name:'[\"\",{\"text\":\"An Arrow\",\"italic\":false,\"color\":\"red\"},{\"text\":\" from Wroclaw\",\"italic\":false,\"color\":\"dark_red\"},{\"text\":\" \",\"italic\":false},{\"text\":\"<\",\"italic\":false}]'}}"
						}
					],
					"name": "minecraft:tipped_arrow"
				}
			]
		},
		{
			"name": "pool2",
			"rolls": 1.0,
			"bonus_rolls": 0.0,
			"entries": [
				{
					"type": "minecraft:item",
					"functions": [
						{
							"function": "minecraft:set_count",
							"count": {
								"type": "minecraft:uniform",
								"min": 1.0,
								"max": 4.0
							},
							"add": false
						}
					],
					"name": "minecraft:nautilus_shell"
				},
				{
					"type": "minecraft:item",
					"functions": [
						{
							"function": "minecraft:set_count",
							"count": {
								"type": "minecraft:uniform",
								"min": 10.0,
								"max": 25.0
							},
							"add": false
						}
					],
					"name": "minecraft:quartz"
				}
			]
		},
		{
			"name": "pool3",
			"rolls": 1.0,
			"bonus_rolls": 0.0,
			"entries": [
				{
					"type": "minecraft:item",
					"functions": [
						{
							"function": "minecraft:enchant_with_levels",
							"conditions": [
								{
									"condition": "minecraft:random_chance",
									"chance": 0.5
								}
							],
							"levels": {
								"type": "minecraft:uniform",
								"min": 10.0,
								"max": 30.0
							},
							"treasure": false
						}
					],
					"name": "minecraft:iron_helmet"
				},
				{
					"type": "minecraft:item",
					"name": "minecraft:leather_horse_armor"
				},
				{
					"type": "minecraft:item",
					"functions": [
						{
							"function": "minecraft:enchant_with_levels",
							"conditions": [
								{
									"condition": "minecraft:random_chance",
									"chance": 0.5
								}
							],
							"levels": {
								"type": "minecraft:uniform",
								"min": 10.0,
								"max": 50.0
							},
							"treasure": false
						}
					],
					"name": "minecraft:leather_helmet"
				},
				{
					"type": "minecraft:item",
					"functions": [
						{
							"function": "minecraft:enchant_with_levels",
							"conditions": [
								{
									"condition": "minecraft:random_chance",
									"chance": 0.5
								}
							],
							"levels": {
								"type": "minecraft:uniform",
								"min": 10.0,
								"max": 30.0
							},
							"treasure": false
						}
					],
					"name": "minecraft:iron_boots"
				},
				{
					"type": "minecraft:item",
					"conditions": [
						{
							"condition": "minecraft:random_chance",
							"chance": 0.3
						}
					],
					"functions": [
						{
							"function": "minecraft:set_nbt",
							"tag": "{CustomPotionColor:8606770,CustomPotionEffects:[{Amplifier:2,Duration:1200,Id:20}],Enchantments:[{id:\"unbreaking\",lvl:3}],display:{Lore:['[\"\",{\"text\":\"Delicious\",\"italic\":false,\"color\":\"white\"}]'],Name:'[\"\",{\"text\":\"Fermented Poop in a Bottle\",\"italic\":false,\"color\":\"#993300\"}]'}}"
						}
					],
					"name": "minecraft:splash_potion"
				}
			]
		}
	]
}